parser/__init__.py
parser/combined.py
vnaddress/__init__.py
vnaddress/combined.py
vnaddress/parser.py
vnaddress/constants/__init__.py
vnaddress/constants/error_dict.py
vnaddress/constants/full_address_error_dict.py
vnaddress/constants/single_vowels.py
vnaddress/constants/standard_addresses.py
vnaddress/constants/standard_single_names.py
vnaddress/functions/__init__.py
vnaddress/functions/combined_process.py
vnaddress/functions/utils.py
vnaddress/functions/acronym_layer/__init__.py
vnaddress/functions/acronym_layer/acronym_execute.py
vnaddress/functions/acronym_layer/constants.py
vnaddress/functions/crf_layer/__init__.py
vnaddress/functions/crf_layer/constants.py
vnaddress/functions/crf_layer/crf_execute.py
vnaddress/functions/crf_layer/preprocess.py
vnaddress/functions/crf_layer/transform_to_dataset.py
vnaddress/functions/crf_layer/word2features.py
vnaddress/functions/crf_layer/xlsx_to_csv.py
vnaddress/functions/spell_correction_layer/__init__.py
vnaddress/functions/spell_correction_layer/generate_error_dict.py
vnaddress/functions/spell_correction_layer/match_word.py
vnaddress/functions/spell_correction_layer/preprocess.py
vnaddress/functions/spell_correction_layer/single_vowel_constants.py
vnaddress/models/finalized_model.sav
vnaddress-1.0.5.data/data/vnaddress/finalized_model.sav
vnaddress-1.0.5.data/scripts/vnas
vnaddress-1.0.5.dist-info/LICENSE
vnaddress-1.0.5.dist-info/METADATA
vnaddress-1.0.5.dist-info/WHEEL
vnaddress-1.0.5.dist-info/top_level.txt
vnaddress-1.0.5.dist-info/RECORD
